aizawa/__init__.py
aizawa/__main__.py
aizawa/core/__init__.py
aizawa/core/executor.py
aizawa/core/validator.py
aizawa/http/__init__.py
aizawa/http/client.py
aizawa/http/headers.py
aizawa/utils/__init__.py
aizawa/utils/banner.py
aizawa/utils/colors.py
aizawa-2.0.0.dist-info/LICENSE
aizawa-2.0.0.dist-info/METADATA
aizawa-2.0.0.dist-info/WHEEL
aizawa-2.0.0.dist-info/entry_points.txt
aizawa-2.0.0.dist-info/RECORD
